wise_utils/__init__.py
wise_utils/common/__init__.py
wise_utils/common/exceptions.py
wise_utils/common/ftp.py
wise_utils/common/log.py
wise_utils/common/mail.py
wise_utils/common/retry_decorator.py
wise_utils/common/setqueue.py
wise_utils/db/__init__.py
wise_utils/db/db_mysql.py
wise_utils/db/db_redis.py
wise_utils/spider/__init__.py
wise_utils/spider/basespider.py
wise_utils/spider/selenium_spider.py
wise_utils/spider/stealth.js
wise_utils-0.3.0.dist-info/LICENSE
wise_utils-0.3.0.dist-info/METADATA
wise_utils-0.3.0.dist-info/WHEEL
wise_utils-0.3.0.dist-info/top_level.txt
wise_utils-0.3.0.dist-info/RECORD
