Metadata-Version: 2.1
Name: wise-utils
Version: 0.3.0
Home-page: https://gitee.com/duquan1995/wise-utils.git
Author: wise-python
Author-email: duke.du@uifox.com.cn
Project-URL: Bug Tracker, https://github.com/pypa/sampleproject/issues
Classifier: Programming Language :: Python :: 3
Classifier: License :: OSI Approved :: MIT License
Classifier: Operating System :: OS Independent
Requires-Python: >3
License-File: LICENSE
Requires-Dist: yagmail (>=0.15.277)
Requires-Dist: orderedset (>=2.0.3)
Requires-Dist: requests (>=2.25.1)
Requires-Dist: urllib3 (>=1.26.7)
Requires-Dist: selenium (>=4.1.0)
Requires-Dist: pyppeteer (~=1.0.2)
Requires-Dist: redis
Requires-Dist: PyMySQL (>=1.0.2)
Requires-Dist: nacos-sdk-python (>=0.1.6)
Requires-Dist: better-exceptions (>=0.3.3)
Requires-Dist: loguru (>=0.6.0)
Requires-Dist: PyVirtualDisplay (>=2.2)
Requires-Dist: undetected-chromedriver (~=3.1.5)
Requires-Dist: webdriver-manager (~=3.5.4)
